LICENSE
MANIFEST.in
README.md
setup.py
pytest_subinterpreter/__init__.py
pytest_subinterpreter/faulthandler.py
pytest_subinterpreter/plugin.py
pytest_subinterpreter.egg-info/PKG-INFO
pytest_subinterpreter.egg-info/SOURCES.txt
pytest_subinterpreter.egg-info/dependency_links.txt
pytest_subinterpreter.egg-info/entry_points.txt
pytest_subinterpreter.egg-info/requires.txt
pytest_subinterpreter.egg-info/top_level.txt
tests/test_simple.py